AlgDiff/__init__.py
AlgDiff/algebraicDifferentiator.py
AlgDiff/test.py
algdiff-2.2.dist-info/METADATA
algdiff-2.2.dist-info/WHEEL
algdiff-2.2.dist-info/licenses/LICENSE
algdiff-2.2.dist-info/RECORD
