Metadata-Version: 2.1
Name: AlgDiff
Version: 2.2
Summary: AlgDiff is a Python class implementing all necessary tools for the design, analysis, and discretization of algebraic differentiators. An interface to Matlab is also provided.
Project-URL: Homepage, https://github.com/aothmane-control/Algebraic-differentiators/tree/master
Author-email: Amine Othmane <amine.othmane@uni-saarland.de>
License: Copyright 2021 Amine Othmane
License-File: LICENSE
Keywords: fir-filters,numerical-differentiation ,numerical-methods ,orthogonal-polynomials
Classifier: License :: OSI Approved :: BSD License
Classifier: Operating System :: OS Independent
Classifier: Programming Language :: Python :: 3
Requires-Python: >=3.0
Requires-Dist: mpmath
Requires-Dist: numpy
Requires-Dist: scipy
